main.py
zelt/__init__.py
zelt/kubernetes/__init__.py
zelt/kubernetes/client.py
zelt/kubernetes/deployer.py
zelt/kubernetes/manifest.py
zelt/kubernetes/manifest_set.py
zelt/kubernetes/storage/__init__.py
zelt/kubernetes/storage/configmap.py
zelt/kubernetes/storage/protocol.py
zelt/kubernetes/storage/s3.py
zelt/zelt.py
zelt-1.2.15.dist-info/entry_points.txt
zelt-1.2.15.dist-info/LICENSE
zelt-1.2.15.dist-info/WHEEL
zelt-1.2.15.dist-info/METADATA
zelt-1.2.15.dist-info/RECORD
