Metadata-Version: 2.1
Name: zelt
Version: 1.2.15
Summary: Zalando end-to-end load tester
Home-page: https://github.com/zalando-incubator/zelt
License: MIT
Keywords: load testing,locust,kubernetes
Author: Brian Maher
Author-email: brian.maher@zalando.de
Requires-Python: >=3.6,<4.0
Classifier: License :: OSI Approved :: MIT License
Classifier: Programming Language :: Python :: 3
Classifier: Programming Language :: Python :: 3.6
Classifier: Programming Language :: Python :: 3.7
Classifier: Programming Language :: Python :: 3.8
Classifier: Topic :: Internet :: WWW/HTTP
Classifier: Topic :: Software Development :: Testing :: Traffic Generation
Provides-Extra: docs
Requires-Dist: boto3 (>=1.9,<2.0)
Requires-Dist: docopt (>=0.6.2,<0.7.0)
Requires-Dist: greenlet (>=0.4.15,<0.5.0)
Requires-Dist: har-transformer (>=1.0,<2.0)
Requires-Dist: kubernetes (>=10.0.1,!=10.1.0,<11)
Requires-Dist: locustio (>=0.9.0,<0.10.0)
Requires-Dist: pyyaml (>=5.1,<6.0)
Requires-Dist: sphinx (>=1.8,<2.0); extra == "docs"
Requires-Dist: sphinx-autodoc-typehints (>=1.6,<2.0); extra == "docs"
Requires-Dist: sphinx-issues (>=1.2,<2.0); extra == "docs"
Requires-Dist: tenacity (>=5.0,<6.0)
Project-URL: Repository, https://github.com/zalando-incubator/zelt
